Workbook
Name _IV65537: '[1]Steel-Circular'!#REF!
Name _IV65537: '[1]Steel-Circular'!#REF!
Name _ll17: #REF!
Name _ll17: #REF!
Name _np3: '[2]Material '!$G$50
Name aggr10: #REF!
Name aggr10: #REF!
Name aggr11: #REF!
Name aggr11: #REF!
Name aggr13: #REF!
Name aggr13: #REF!
Name aggr2: #REF!
Name aggr2: #REF!
Name aggr2.36: #REF!
Name aggr2.36: #REF!
Name aggr20: #REF!
Name aggr20: #REF!
Name aggr22: #REF!
Name aggr22: #REF!
Name aggr26: #REF!
Name aggr26: #REF!
Name aggr40: #REF!
Name aggr40: #REF!
Name aggr53: #REF!
Name aggr53: #REF!
Name aggr6: #REF!
Name aggr6: #REF!
Name aggr63: #REF!
Name aggr63: #REF!
Name agrr10: #REF!
Name agrr10: #REF!
Name agrr63mm: #REF!
Name agrr63mm: #REF!
Name ballies: '[2]Material '!$G$31
Name bhistee: #REF!
Name bhistee: #REF!
Name bhisti: #REF!
Name bhisti: #REF!
Name bitumen: #REF!
Name bitumen: #REF!
Name bitumen6070: #REF!
Name bitumen6070: #REF!
Name bitumenboiler: #REF!
Name bitumenboiler: #REF!
Name bitumenemul: #REF!
Name bitumenemul: #REF!
Name blacksmith: #REF!
Name blacksmith: #REF!
Name blacksmithhelper: #REF!
Name blacksmithhelper: #REF!
Name blaster: #REF!
Name blaster: #REF!
Name bondstone: '[2]Material '!$G$40
Name boulder: #REF!
Name boulder: #REF!
Name bricks: #REF!
Name bricks: #REF!
Name carpenter: #REF!
Name carpenter: #REF!
Name carpenter1: #REF!

Sheet ABSTRACT OF COST
A1: ABSTRACT OF COST
A2: S# | B2: Description | C2: Total Amount | D2: Amount (Cr.)
A3: 1 | B3: SITE CLEARANCE | C3: =BOQ!AL83 -> 0 | D3: =(C3/10^7) -> 0
A4: 2 | B4: EARTH WORK, EROSION CONTROL AND DRAINAGE | C4: =BOQ!AL144 -> 0 | D4: =(C4/10^7) -> 0
A5: 3 | B5: SUB-BASES, BASES ( NON- BITUMINOUS) AND SHOULDERS | C5: =BOQ!AL243+BOQ!AL1585 -> 0 | D5: =(C5/10^7) -> 0
A6: 4 | B6: BASES, SURFACE COURSES AND CEMENT CONCRETE PAVEMENTS | C6: =BOQ!AL310+BOQ!AL318 -> 0 | D6: =(C6/10^7) -> 0
A7: 5 | B7: CULVERTS & BOX CELL STRUCTURES | C7: =BOQ!AL634+BOQ!AL1462 -> 0 | D7: =(C7/10^7) -> 0
A8: 6 | B8: BRIDGES / ROB | C8: =BOQ!AL1169+BOQ!AL1239+BOQ!AL1361 -> 0 | D8: =(C8/10^7) -> 0
A9: 6A | B9: REPAIR, REPAIR AND REHABILITATION OF EXISTING BRIDGES | C9: =BOQ!AL1512 -> 0 | D9: =(C9/10^7) -> 0
A10: 7 | B10: DRAINAGE, RIVER TRAINING AND PROTECTION WORKS | C10: =BOQ!AL399+BOQ!AL1485+BOQ!AL1584 -> 0 | D10: =(C10/10^7) -> 0
A11: 8 | B11: MAINTENANCE OF ROADS | C11: =BOQ!AL671 -> 0 | D11: =(C11/10^7) -> 0
A12: 9 | B12: TRAFFIC SIGNS, MARKINGS & OTHER ROAD APPURTENANCES | C12: =BOQ!AL583 -> 0 | D12: =(C12/10^7) -> 0
A13: 10 | B13: TUNNEL WORKS | C13: =BOQ!AL1554 -> 0 | D13: =(C13/10^7) -> 0
A14: 11 | B14: HORTICULTURE , ENVIRONMENTAL & SAFETY MANAGEMENT AND BIO ENGINEERING | C14: =BOQ!AL698+BOQ!AL1580 -> 0 | D14: =(C14/10^7) -> 0
A15: A) | B15: TOTAL COST (INR) | C15: =SUM(C3:C14) -> 0 | D15: =(C15/10^7) -> 0
A16: B) | B16: GST ON TOTAL COST 18% of A | C16: =C15*18% -> 0 | D16: =(C16/10^7) -> 0
B17: TOTAL CONSTRUCTION COST (A+B) | C17: =SUM(C15:C16) -> 0 | D17: =(C17/10^7) -> 0

Sheet BOQ
A1: Sub_Bill_Id | B1: Item No. | C1: Description | D1: Unit | E1: Main Carriageway | F1: Service Road
A3: 2.00 | C3: CHAPTER-2 - SITE CLEARANCE
A4: 2.01.A | B4: 2.01 (A) | C4: Cutting of trees, excluding removal of stumps and roots of trees (Cutting of trees, trunks and branches excluding removal of stumps and roots of trees and stacking of serviceable material with all lifts and up to a lead of 1000 mtrs )
A5: 2.01.A.i | B5: (i) | C5: Girth from 300 mm to 600 mm | D5: each
A6: 2.01.A.ii | B6: (ii) | C6: Girth from 600 mm to 900 mm | D6: each
A7: 2.01.A.iii | B7: (iii) | C7: Girth from 900 mm to 1800 mm | D7: each
A8: 2.01.A.iv | B8: (iv) | C8: Girth above 1800 mm | D8: each
A9: 2.01.B | B9: 2.01 (B) | C9: Cutting of Trees, including Cutting of Trunks, Branches and Removal (Removal of stumps, roots, stacking of serviceable material with all lifts and up to a lead of 1000 metres and earth filling in the depression/pit.)
A10: 2.01.B.i | B10: (i) | C10: Girth from 300 mm to 600 mm | D10: each
A11: 2.01.B.ii | B11: (ii) | C11: Girth from 600 mm to 900 mm | D11: each
A12: 2.01.B.iii | B12: (iii) | C12: Girth from 900 mm to 1800 mm | D12: each
A13: 2.01.B.iv | B13: (iv) | C13: Girth above 1800 mm | D13: each
A14: 2.02 | B14: 2.02 | C14: Clearing Grass and Removal of Rubbish (Clearing grass and removal of rubbish up to a distance of 50 metres outside the periphery of the area . ) | D14: hectare
A15: 2.03 | B15: 2.03 | C15: Clearing and Grubbing Road Land .(Clearing and grubbing road land including uprooting rank vegetation, grass, bushes, shrubs, saplings and trees girth up to 300 mm, removal of stumps of trees cut earlier and disposal of unserviceable materials and stacking of serviceable material to be used or auctioned up to a lead of 1000 metres including removal and disposal of top organic soil not exceeding 150 mm in thickness.)
A16: 2.03.i | B16: (i) | C16: By Manual Means:-
A17: 2.03.i.A | B17: A | C17: In area of light jungle | D17: hectare
A18: 2.03.i.B | B18: B | C18: In area of thorny jungle | D18: hectare
A19: 2.03.ii | B19: (ii) | C19: By Mechanical Meansby by Dozer
A20: 2.03.ii.A | B20: A | C20: In area of light jungle | D20: hectare
A21: 2.03.ii.B | B21: B | C21: In area of thorny jungle | D21: hectare
A22: 2.3.iii | B22: (iii) | C22: By Mechanical Means using by motor Grader
A23: 2.3.iii.A | B23: A | C23: In area of light jungle | D23: hectare
A24: 2.3.iii.B | B24: B | C24: In area of thorny jungle | D24: hectare
A25: 2.04 | B25: 2.04 | C25: Dismantling of Structures (Dismantling of existing structures like culverts, bridges, retaining walls and other structure comprising of masonry, cement concrete, wood work, steel work, including T&P and scaffolding wherever necessary, sorting the dismantled material, disposal of unserviceable material and stacking the serviceable material with all lifts and lead of 1000 metres)
A26: 2.04.i | B26: (i) | C26: Lime /Cement Concrete
A27: 2.04.I | B27: I | C27: By Manual Means
A28: 2.04.i.I.A | B28: A | C28: Lime Concrete, cement concrete grade M-10 and below | D28: cum
A29: 2.04.i.I.B | B29: B | C29: Cement Concrete Grade M-15 & M-20 | D29: cum
A30: 2.04.i.I.C | B30: C | C30: Prestressed / Reinforced cement concrete grade M-20 & above | D30: cum
A31: 2.04.i.II | B31: II | C31: By Mechanical Means for items No. 2.04( b) & ( c)
A32: 2.04.i.II.A | B32: A | C32: Cement Concrete Grade M-15 & M-20 | D32: cum
A33: 2.04.i.II.B | B33: B | C33: Prestressed / Reinforced cement concrete grade M-20 & above | D33: cum
A34: 2.04.ii | B34: (ii) | C34: Dismantling Brick / Tile work
A35: 2.04.ii.A | B35: A | C35: In lime mortar | D35: cum
A36: 2.04.ii.B | B36: B | C36: In cement mortar | D36: cum
A37: 2.04.ii.C | B37: C | C37: In mud mortar | D37: cum
A38: 2.04.ii.D | B38: D | C38: Dry brick pitching or brick soling | D38: cum
A39: 2.04.iii | B39: (iii) | C39: Dismantling Stone Masonry
A40: 2.04.iii.A | B40: A | C40: Rubble stone masonry in lime mortar | D40: cum
A41: 2.04.iii.B | B41: B | C41: Rubble stone masonry in cement mortar. | D41: cum
A42: 2.04.iii.C | B42: C | C42: Rubble Stone Masonry in mud mortar. | D42: cum
A43: 2.04.iii.D | B43: D | C43: Dry rubble masonry | D43: cum
A44: 2.04.iii.E | B44: E | C44: Dismantling stone pitching/ dry stone spalls. | D44: cum
A45: 2.04.iii.F | B45: F | C45: Dismantling boulders laid in wire crates including opening of crates and stacking dismantled materials. | D45: cum
A46: 2.04.iii.II | B46: II | C46: By Mechanical Means for items No. 2.04 (iii)
A47: 2.04.iii.II.A | B47: A | C47: Dismantling Brick / Tile work/ rubble masonary/ pitching/ etc by mechanical means | D47: cum
A48: 2.04.iv | B48: (iv) | C48: Wood work wrought framed and fixed in frames of trusses upto a height of 5 m above plinth level | D48: cum
A49: 2.04.v | B49: (v) | C49: Steel work in all types of sections upto a height of 5 m above plinth level excluding cutting of rivet.
A50: 2.04.v.A | B50: A | C50: Including dismembering | D50: tonne
A51: 2.04.v.B | B51: B | C51: Excluding dismembering. | D51: tonne
A52: 2.04.v.C | B52: C | C52: Extra over item No( V ) A and( V ) B for cutting rivets. | D52: tonne
A53: 2.04.vi | B53: (vi) | C53: Scraping of bricks dismantled from brick work including stacking.
A54: 2.04.vi.A | B54: A | C54: In lime/Cement mortar | D54: 1000 numbers
A55: 2.04.vi.B | B55: B | C55: In mud mortar | D55: 1000 numbers
A56: 2.04.vii | B56: (vii) | C56: Scraping of Stone from dismantled stone masonry
A57: 2.04.vii.A | B57: A | C57: In cement and lime mortar | D57: cum
A58: 2.04.vii.B | B58: B | C58: In Mud mortar | D58: cum
A59: 2.04.viii | B59: (viii) | C59: Scarping plaster in lime or cement mortar from brick/ stone masonry | D59: sqm
A60: 2.04.ix | B60: (ix) | C60: Removing all type of hume pipes and stacking within a lead of 1000 metres including earthwork and dismantling of masonry works.
A61: 2.04.ix.A | B61: A | C61: Up to 600 mm dia | D61: metre
A62: 2.04.ix.B | B62: B | C62: Above 600 mm to 900 mm dia | D62: metre
A63: 2.04.ix.C | B63: C | C63: Above 900 mm | D63: metre
A64: 2.05 | B64: 2.05 | C64: Dismantling of Flexible Pavements (Dismantling of flexible pavements and disposal of dismantled materials up to a lead of 1000 metres, stacking serviceable and unserviceable materials separately)
A65: 2.05.I | B65: I | C65: By Manual Means
A66: 2.05.I.A | B66: A | C66: Bituminous courses | D66: cum
A67: 2.05.I.B | B67: B | C67: Granular courses | D67: cum
A68: 2.05.II | B68: II | C68: By Mechanical Means
A69: 2.05.II.A | B69: A | C69: Bituminous course | D69: cum
A70: 2.05.II.B | B70: B | C70: Granular courses | D70: cum
A71: 2.06 | B71: 2.06 | C71: Dismantling of Cement Concrete Pavement (Dismantling of cement concrete pavement by mechanical means using pneumatic tools, breaking to pieces not exceeding 0.02 cum in volume and stock piling at designated locations and disposal of dismantled materials up to a lead of 1000 metres, stacking serviceable and unserviceable materials separately) | D71: cum
A72: 2.07 | B72: 2.07 | C72: Dismantling Guard Rails (Dismantling guard rails by manual means and disposal of dismantled material with all lifts and up to a lead of 1000 metres, stacking serviceable materials and unserviceable materials separately.) | D72: metre
A73: 2.08 | B73: 2.08 | C73: Dismantling Kerb Stone (Dismantling kerb stone by manual means and disposal of dismantled material with all lifts and up to a lead of 1000 metre) | D73: metre
A74: 2.09 | B74: 2.09 | C74: Dismantling Kerb Stone channel (Dismantling kerb stone channel by manual means and disposal of dismantled material with all lifts and up to a lead of 1000 metre) | D74: metre
A75: 2.10 | B75: 2.10 | C75: Dismantling Kilometre Stone (Dismantling of kilometre stone including cutting of earth, foundation and disposal of dismantled material with all lifts and lead upto 1000 m and back filling of pit.)
A76: 2.10.A | B76: A | C76: 5th KM stone | D76: each
A77: 2.10.B | B77: B | C77: Ordinary KM Stone | D77: each
A78: 2.10.C | B78: C | C78: Hectometre Stone | D78: each
A79: 2.11 | B79: 2.11 | C79: Dismantling of Fencing (Dismantling of barbed wire fencing/ wire mesh fencing including posts, foundation concrete, back filling of pit by manual means including disposal of dismantled material with all lifts and up to a lead of 1000 metres, stacking serviceable material and unserviceable material separately. ) | D79: metre
A80: 2.12 | B80: 2.12 | C80: Dismantling of CI Water Pipe Line (Dismantling of CI water pipe line 600 mm dia including disposal with all lifts and lead upto 1000 metres and stacking of serviceable material and unserviceable material separately under supervision of concerned department) | D80: metre
A81: 2.13 | B81: 2.13 | C81: Removal of Cement Concrete Pipe of Sewer Gutter (Removal of cement concrete pipe of sewer gutter 1500 mm dia under the supervision of concerned department including disposal with all lifts and up to a lead of 1000 metres and stacking of serviceable and unserviceable material separately but excluding earth excavation and dismantling of masonry works.) | D81: metre
A82: 2.14 | B82: 2.14 | C82: Removal of Telephone / Electric Poles and Lines (Removal of telephone / Electric poles including excavation and dismantling of foundation concrete and lines under the supervision of concerned department, disposal with all lifts and up to a lead of 1000 metres and stacking the serviceable and unserviceable material separately) | D82: each
A83: 3 | C83: CHAPTER-3 - EARTH WORK, EROSION CONTROL AND DRAINAGE
A84: 3.01 | B84: 3.01 | C84: Excavation in Soil by Manual Means. (Excavation for roadway in soil using manual means including loading in truck for carrying of cut earth to embankment site with all lifts and lead upto1000 metres.) | D84: cum
A85: 3.02 | B85: 3.02 | C85: Excavation in ordinary rock by manual means (Excavation in ordinary rock using manual means including loading in a truck and carrying of excavated material to embankment site with in all lifts and leads upto 1000 metres ) | D85: cum
A86: 3.03 | B86: 3.03 | C86: Excavation in Soil with Dozer with lead upto 1000 metres (EExcavation for road way in soil by mechanical means including cutting and transporting the earth to site of embankment/dumping area with lead upto 1000 metres, including trimming bottom and side slopes in accordance with requirements of lines, grades and cross sections.) | D86: cum
A87: 3.04 | B87: 3.04 | C87: Excavation in Ordinary Rock with Dozer with lead upto 1000 metres (Excavation for roadway in ordinary rock by deploying a dozer, including cutting and transporting the earth to site of embankment/dumping area with lead upto 1000 metres, trimming bottom and side slopes in accordance with the requirements of lines, grades and cross sections.) | D87: cum
A88: 3.05 | B88: 3.05 | C88: Excavation in Hard Rock (requiring blasting) with disposal upto 1000 metres (Excavation for roadway in hard rock (requiring blasting) by drilling, blasting and breaking, trimming of bottom and side slopes in accordance with requirements of lines, grades and cross sections, loading and disposal of cut road with in all lifts and leads upto 1000 metres ) | D88: cum
A89: 3.06 | B89: 3.06 | C89: Excavation in Soil using Hydraulic Excavator and Tippers with disposal upto 1000 metres. (Excavation for roadwork in soil with hydraulic excavator including cutting and loading in tippers, trimming bottom and side slopes, in accordance with requirements of lines, grades and cross sections, and transporting to the embankment location within all lifts and lead upto 1000m) | D89: cum
A90: 3.07 | B90: 3.07 | C90: Excavation in Ordinary Rock using Hydraulic Excavator and Tippers with disposal upto 1000 metres. (Excavation for roadwork in soil with hydraulic excavator including cutting and loading in tippers, trimming bottom and side slopes, in accordance with requirements of lines, grades and cross sections, and transporting to the embankment location within all lifts and lead upto 1000m.) | D90: cum
A91: 3.08 | B91: 3.08 | C91: Excavation in Hard Rock (blasting prohibited) (Excavation for roadwork in Hard Rock (blasting prohibited) with hydraulic excavator including cutting and loading in tippers, trimming bottom and side slopes, in accordance with requirements of lines, grades and cross sections, and transporting to the embankment location within all lifts and lead upto 1000 m.)
A92: 3.08.A | B92: A | C92: Mechanised | D92: cum
A93: 3.08.B | B93: B | C93: Manual Method | D93: cum
A94: 3.09 | B94: 3.09 | C94: Excavation in Hard Rock (controlled blasting) with disposal upto 1000 metres (EExcavation for roadway in hard rock (requiring blasting) by drilling, blasting and breaking, trimming of bottom and side slopes in accordance with requirements of lines, grades and cross sections, loading and disposal of cut road with in all lifts and leads upto 1000 metres ) | D94: cum
A95: 3.10 | B95: 3.10 | C95: Excavation in Marshy Soil (Excavation for roadwork in Marshy Soil with hydraulic excavator including cutting and loading in tippers, trimming bottom and side slopes, in accordance with requirements of lines, grades and cross sections, and transporting to the embankment location within all lifts and lead upto 1000 m.) | D95: cum
A96: 3.11 | B96: 3.11 | C96: Removal of Unserviceable Soil with Disposal upto 1000 metres (Removal of unserviceable soil including excavation, loading and disposal upto 1000 metres lead but excluding replacement by suitable soil which shall be paid separately as per clause 305..) | D96: cum
A97: 3.12 | B97: 3.12 | C97: Pre-splitting of Rock Excavation Slopes (Carrying out excavation in hard rock to achieve a specified slope of the rock face by controlled use of explosives and blasting accessories in properly aligned and spaced drill holes, collection of the excavated rock by a dozer, loading in tipper by a front end loader and disposing of the material with all lifts and lead upto 1000 m, all as specified in clause No. 303) | D97: sqm
A98: 3.13 | B98: 3.13 | C98: Excavation for Structures (Earth work in excavation of foundation of structures as per drawing and technical specification, including setting out, construction of shoring and bracing, removal of stumps and other deleterious matter, dressing of sides and bottom, backfilling the excavation earth to the extent required and utilising the remaining earth locally for road work.)
A99: 3.13.i | B99: (i) | C99: Ordinary soil
A100: 3.13.i.A | B100: A | C100: Manual Means (Depth upto 3 m) | D100: cum
A101: 3.13.i.B | B101: B | C101: Mechanical Means (Depth upto 3 m) | D101: cum
...

Sheet Markert Rate
B2: Sl. No. | C2: Item Description | D2: Unit | E2: Rate (Rs.)
B3: MR01 | C3: Construction of restaurant, workshop, first aid room, shop etc. in truck parking area complete as per drg. and direction of the Engineer. | D3: Sqm | E3: 10000
B4: MR02 | C4: Providing Telephone booth complete as per specifications and direction of Engineer. | D4: Nos. | E4: 100000
B5: MR03 | C5: Providing & fixing tube well, complete as per drawing and additional specifictions. | D5: Nr. | E5: 100000
B6: MR04 | C6: Providing a Drinking Water Kiosk complete as per drawing & specification. | D6: Nr. | E6: 200000
B7: MR05 | C7: Providing and fixing of litter bins in Truck lay Bye locations complete as per drawing or as directed by the engineer. | D7: Nr. | E7: 50000
B8: MR06 | C8: Construction of toilet block provided with fittings and fixtures complete in truck parking area complete as per drg. and direction of the Engineer. | D8: Nr. | E8: 100000
B9: MR07 | C9: Construction of Open lined U - Drain in truck laybye area complete as shown in drawing and technical specification clause 309. | D9: Meter | E9: 8000
B10: MR08 | C10: Providing shelters for bus passengers as per drawing and MORT&H Specifications section 300, 1500, 1600 and 1700. | D10: Nr. | E10: 80000
B11: MR09 | C11: Providing & fixing guard railing with tubular steel sections at foot path / medians / islands etc including foundation concrete and painting with approved paint etc. all complete as per drawing & MORT&H Specifications Clauses 808, 300, 1500, 1700 & 1900. | D11: Meter | E11: 1800
B12: MR10 | C12: Toll Booth at Tollplaza | D12: Nr. | E12: 200000
B13: MR11 | C13: Barrier gates at Tollplaza For 3.2 m wide toll lane | D13: Nr. | E13: 150000
B14: MR12 | C14: Barrier gates at Tollplaza For 4.5 m wide toll lane | D14: Nr. | E14: 200000
... B22: MR20 | C22: Ambulances at Toll Plaza | D22: Nr. | E22: 2000000
B23: MR21 | C23: Cranes at Toll Plaza | D23: Nr. | E23: =80000*15*12+(4*30*180)*4*65 -> 20016000
B24: MR22 | C24: Electronic Toll Connection (ETC lanes) at Toll Plaza | D24: Nr. | E24: 200000
B25: MR23 | C25: Intercom facility at Toll Plaza | D25: Nr. | E25: 100000
B26: MR24 | C26: Weigh Bridge | D26: Nr. | E26: 350000
B27: MR25 | C27: Car Parking area | D27: Sqm | E27: 5000
B28: MR26 | C28: Generator room | D28: Sqm | E28: 10000
B29: MR27 | C29: Base Maintainance Camp | D29: Sqm | E29: 1000
B30: MR28 | C30: Toll plaza equipment | D30: Lane | E30: 100000
B31: MR29 | C31: Electrification And Air conditioning for toll Booth and toll Plaza | D31: LS | E31: 150000
B32: MR30 | C32: Bull nose crash barrier | D32: Nr. | E32: 3000
B33: MR31 | C33: Standby Generator at Toll Plaza | D33: Nr. | E33: 500000
B34: MR32 | C34: CCTV camera installed at each booth | D34: Nr. | E34: 150000
B35: MR33 | C35: T1 for Toll Road Start | D35: Nr. | E35: 250000
... B47: MR45 | C47: PVC Roof Sheet at FOB | D47: Sqm | E47: 160
